{
  "version": "1.0",
  "id": "2daecc19-6e25-42bf-8464-150199f21d3e",
  "label": "Message: %display_message%",
  "type": "",
  "autoExpand": false,
  "skipEveryInstanceFiles": false,
  "limitToAllowedChildren": false,
  "autoGenerate": false,
  "key": "",
  "infoHtml": "\u003ch2\u003eDisplay message\u003c/h2\u003e\u003cp\u003e\u003ca target\u003d\"_blank\" href\u003d\"https://github.com/infraxys-modules/infraxys-by-example/modules/infraxys-a-to-z/01-hello-world/README.md\"\u003eOpen the instructions\u003c/a\u003e\u003c/p\u003e",
  "attributes": [
    {
      "id": "b4235a49-54a1-4310-a99b-1efadf4e26cd",
      "name": "display_message",
      "caption": "Display message",
      "type": "java.lang.String",
      "formColumn": 1,
      "formOrder": 1100,
      "visibility": "ALWAYS VISIBLE",
      "writability": "ALWAYS",
      "required": true,
      "isPartOfKey": false,
      "listOfValues": "",
      "cacheMinutes": 0,
      "referenceFilter": "",
      "referenceValueAttributeName": "",
      "referenceChildIdFilter": "",
      "newItemsAllowed": false,
      "parseWithVelocity": true,
      "cloneAttribute": true,
      "inputPrompt": "\u003cEnter a message here\u003e",
      "tooltip": "\u003ch2\u003eDisplay message\u003c/h2\u003e\u003cp\u003eEnter the message to display.\u003c/p\u003e",
      "scope": "Instance",
      "defaultValue": ""
    }
  ],
  "files": [
    {
      "id": "ac755e01-bf49-4a9e-b32d-864827296d4b",
      "filename": "display-message.sh",
      "menuCaption": "Display message",
      "directory": "",
      "runsIndependent": false,
      "runsParallel": false,
      "runBeforeIndependentActions": false,
      "parseWithVelocity": false,
      "executable": true,
      "saveWith": "CURRENT INSTANCE",
      "isInteractive": false,
      "hideRunnerWindow": false,
      "timeoutSeconds": 3600,
      "key": "",
      "menuOrder": 100,
      "menuSeparatorBefore": false,
      "hideFromInstanceActionsMenu": false,
      "hideFromBottomMenu": false,
      "menuPath": "",
      "dockerImage": "",
      "customCommand": ""
    },
    {
      "id": "e3eb4934-6ae8-430a-ac93-011f3d6a2b0e",
      "filename": "display-popup.sh",
      "includeName": "",
      "menuCaption": "Display popup",
      "directory": "",
      "runsIndependent": false,
      "runsParallel": false,
      "runBeforeIndependentActions": false,
      "parseWithVelocity": false,
      "executable": true,
      "saveWith": "CURRENT INSTANCE",
      "isInteractive": false,
      "hideRunnerWindow": false,
      "timeoutSeconds": 3600,
      "key": "",
      "menuOrder": 200,
      "menuSeparatorBefore": true,
      "hideFromInstanceActionsMenu": false,
      "hideFromBottomMenu": false,
      "menuPath": "",
      "dockerImage": "",
      "customCommand": ""
    }
  ],
  "allowedChildren": []
}